provide/__init__.py
provide/testkit/__init__.py
provide/testkit/__main__.py
provide/testkit/_blocker.py
provide/testkit/_early_init.py
provide/testkit/_install_blocker.py
provide/testkit/_install_pth.py
provide/testkit/conftest.py
provide/testkit/main.py
provide/testkit/provide_testkit_init.pth
provide/testkit/py.typed
provide/testkit/pytest_plugin.py
provide/testkit/archive/__init__.py
provide/testkit/archive/fixtures.py
provide/testkit/base/__init__.py
provide/testkit/base/foundation.py
provide/testkit/base/harness.py
provide/testkit/base/minimal.py
provide/testkit/chaos/__init__.py
provide/testkit/chaos/concurrency_strategies.py
provide/testkit/chaos/fixtures.py
provide/testkit/chaos/io_strategies.py
provide/testkit/chaos/strategies.py
provide/testkit/chaos/time_strategies.py
provide/testkit/cli/__init__.py
provide/testkit/cli/runner.py
provide/testkit/cli/testing.py
provide/testkit/common/__init__.py
provide/testkit/common/fixtures.py
provide/testkit/crypto/__init__.py
provide/testkit/crypto/fixtures.py
provide/testkit/file/__init__.py
provide/testkit/file/content_fixtures.py
provide/testkit/file/directory_fixtures.py
provide/testkit/file/fixtures.py
provide/testkit/file/special_fixtures.py
provide/testkit/file/temp.py
provide/testkit/hub/__init__.py
provide/testkit/hub/fixtures.py
provide/testkit/logger/__init__.py
provide/testkit/logger/hooks.py
provide/testkit/logger/mocks.py
provide/testkit/logger/reset.py
provide/testkit/mocking/__init__.py
provide/testkit/mocking/fixtures.py
provide/testkit/mocking/time.py
provide/testkit/process/__init__.py
provide/testkit/process/async_fixtures.py
provide/testkit/process/fixtures.py
provide/testkit/process/script_assertions.py
provide/testkit/process/script_fixtures.py
provide/testkit/process/subprocess_fixtures.py
provide/testkit/process/system_fixtures.py
provide/testkit/quality/__init__.py
provide/testkit/quality/artifacts.py
provide/testkit/quality/base.py
provide/testkit/quality/cli.py
provide_testkit-0.0.1114.dist-info/licenses/LICENSE
provide_testkit-0.0.1114.dist-info/METADATA
provide_testkit-0.0.1114.dist-info/WHEEL
provide_testkit-0.0.1114.dist-info/entry_points.txt
provide_testkit-0.0.1114.dist-info/top_level.txt
provide_testkit-0.0.1114.dist-info/RECORD
